LICENSE
luxhouse/__init__.py
luxhouse/database.py
luxhouse/model.py
luxhouse/scrapping.py
luxhouse-0.1.8.dist-info/LICENSE
luxhouse-0.1.8.dist-info/WHEEL
luxhouse-0.1.8.dist-info/METADATA
luxhouse-0.1.8.dist-info/RECORD
