Metadata-Version: 2.1
Name: luxhouse
Version: 0.1.8
Summary: Scrapper to get information about housing market in Luxembourg and around.
License: Apache-2.0
Author: Renaud Rwemalika
Author-email: renaudrwemalika@gmail.com
Requires-Python: >=3.10,<4.0
Classifier: License :: OSI Approved :: Apache Software License
Classifier: Programming Language :: Python :: 3
Classifier: Programming Language :: Python :: 3.10
Classifier: Programming Language :: Python :: 3.11
Requires-Dist: bs4 (>=0.0.1,<0.0.2)
Requires-Dist: html5lib (>=1.1,<2.0)
Requires-Dist: pandas (>=1.5.0,<2.0.0)
Requires-Dist: requests (>=2.28.1,<3.0.0)
